setup.py
django_tinyuuidfield.egg-info/PKG-INFO
django_tinyuuidfield.egg-info/SOURCES.txt
django_tinyuuidfield.egg-info/dependency_links.txt
django_tinyuuidfield.egg-info/not-zip-safe
django_tinyuuidfield.egg-info/top_level.txt
tinyuuidfield/__init__.py
tinyuuidfield/fields.py